externaloverlayrep.py
externaloverlayrep-1.0.0.dist-info/WHEEL
externaloverlayrep-1.0.0.dist-info/METADATA
externaloverlayrep-1.0.0.dist-info/RECORD
